{"cameraMode":{"drawMode":0,"name":"Shaded","section":"Shading Mode"},"sceneLighting":true,"audioPlay":false,"sceneViewState":{"showFog":true,"showMaterialUpdate":false,"showSkybox":true,"showFlares":true,"showImageEffects":true,"showParticleSystems":true,"showVisualEffectGraphs":true,"m_FxEnabled":true},"in2DMode":false,"pivot":{"x":-232.32489013671876,"y":-361.91107177734377,"z":186.80673217773438},"rotation":{"x":-0.379029244184494,"y":0.4434865713119507,"z":-0.21454505622386933,"w":-0.7834052443504334},"size":329.9589538574219,"orthographic":false}